seqdatasets/__init__.py
seqdatasets/_datasets.py
seqdatasets/_utils.py
seqdatasets/datasets.csv
seqdatasets/random1000/random1000_seqs.tsv
seqdatasets/random1000/random1000_seqs.zarr/.zattrs
seqdatasets/random1000/random1000_seqs.zarr/.zgroup
seqdatasets/random1000/random1000_seqs.zarr/.zmetadata
seqdatasets/random1000/random1000_seqs.zarr/activity_0/.zarray
seqdatasets/random1000/random1000_seqs.zarr/activity_0/.zattrs
seqdatasets/random1000/random1000_seqs.zarr/activity_0/0
seqdatasets/random1000/random1000_seqs.zarr/activity_1/.zarray
seqdatasets/random1000/random1000_seqs.zarr/activity_1/.zattrs
seqdatasets/random1000/random1000_seqs.zarr/activity_1/0
seqdatasets/random1000/random1000_seqs.zarr/activity_2/.zarray
seqdatasets/random1000/random1000_seqs.zarr/activity_2/.zattrs
seqdatasets/random1000/random1000_seqs.zarr/activity_2/0
seqdatasets/random1000/random1000_seqs.zarr/activity_3/.zarray
seqdatasets/random1000/random1000_seqs.zarr/activity_3/.zattrs
seqdatasets/random1000/random1000_seqs.zarr/activity_3/0
seqdatasets/random1000/random1000_seqs.zarr/activity_4/.zarray
seqdatasets/random1000/random1000_seqs.zarr/activity_4/.zattrs
seqdatasets/random1000/random1000_seqs.zarr/activity_4/0
seqdatasets/random1000/random1000_seqs.zarr/activity_5/.zarray
seqdatasets/random1000/random1000_seqs.zarr/activity_5/.zattrs
seqdatasets/random1000/random1000_seqs.zarr/activity_5/0
seqdatasets/random1000/random1000_seqs.zarr/activity_6/.zarray
seqdatasets/random1000/random1000_seqs.zarr/activity_6/.zattrs
seqdatasets/random1000/random1000_seqs.zarr/activity_6/0
seqdatasets/random1000/random1000_seqs.zarr/activity_7/.zarray
seqdatasets/random1000/random1000_seqs.zarr/activity_7/.zattrs
seqdatasets/random1000/random1000_seqs.zarr/activity_7/0
seqdatasets/random1000/random1000_seqs.zarr/activity_8/.zarray
seqdatasets/random1000/random1000_seqs.zarr/activity_8/.zattrs
seqdatasets/random1000/random1000_seqs.zarr/activity_8/0
seqdatasets-0.1.2.dist-info/LICENSE
seqdatasets-0.1.2.dist-info/METADATA
seqdatasets-0.1.2.dist-info/WHEEL
seqdatasets-0.1.2.dist-info/RECORD
